setup.py
multipolyfit/__init__.py
multipolyfit/core.py
multipolyfit.egg-info/PKG-INFO
multipolyfit.egg-info/SOURCES.txt
multipolyfit.egg-info/dependency_links.txt
multipolyfit.egg-info/not-zip-safe
multipolyfit.egg-info/top_level.txt