Metadata-Version: 1.0
Name: multipolyfit
Version: 0.0.1
Summary: Multivariate Polynomial fitting with NumPy
Home-page: http://github.com/mrocklin/multipolyfit
Author: Matthew Rocklin
Author-email: mrocklin@gmail.com
License: BSD
Platform: UNKNOWN
